payos/__init__.py
payos/_async_client.py
payos/_client.py
payos/_core/__init__.py
payos/_core/exceptions.py
payos/_core/models.py
payos/_core/pagination.py
payos/_core/request_options.py
payos/_crypto/__init__.py
payos/_crypto/provider.py
payos/_version.py
payos/resources/__init__.py
payos/resources/_base.py
payos/resources/v1/__init__.py
payos/resources/v1/payouts/__init__.py
payos/resources/v1/payouts/batch/__init__.py
payos/resources/v1/payouts/batch/batch.py
payos/resources/v1/payouts/payouts.py
payos/resources/v1/payouts_account/__init__.py
payos/resources/v1/payouts_account/payouts_account.py
payos/resources/v2/__init__.py
payos/resources/v2/payment_requests/__init__.py
payos/resources/v2/payment_requests/invoices/__init__.py
payos/resources/v2/payment_requests/invoices/invoices.py
payos/resources/v2/payment_requests/payment_requests.py
payos/resources/webhooks/__init__.py
payos/resources/webhooks/webhooks.py
payos/types/__init__.py
payos/types/common.py
payos/types/v1/__init__.py
payos/types/v1/payouts/__init__.py
payos/types/v1/payouts/batch/__init__.py
payos/types/v1/payouts/batch/batch.py
payos/types/v1/payouts/payouts.py
payos/types/v1/payouts_account/__init__.py
payos/types/v1/payouts_account/payouts_account.py
payos/types/v2/__init__.py
payos/types/v2/payment_requests/__init__.py
payos/types/v2/payment_requests/invoices/__init__.py
payos/types/v2/payment_requests/invoices/invoices.py
payos/types/v2/payment_requests/payment_requests.py
payos/types/webhooks/__init__.py
payos/types/webhooks/webhook.py
payos/utils/__init__.py
payos/utils/casting.py
payos/utils/env.py
payos/utils/json_utils.py
payos/utils/logs.py
payos/utils/validation.py
payos-1.0.1.dist-info/WHEEL
payos-1.0.1.dist-info/METADATA
payos-1.0.1.dist-info/RECORD
