Metadata-Version: 2.3
Name: payos
Version: 1.0.1
Summary: payOS Python SDK
Keywords: payos,payment,payos-python,sdk,python
Author: payOS Team
Author-email: payOS Team <support@payos.vn>
Classifier: Intended Audience :: Developers
Classifier: License :: OSI Approved :: MIT License
Classifier: Operating System :: OS Independent
Classifier: Programming Language :: Python :: 3
Classifier: Programming Language :: Python :: 3.9
Classifier: Programming Language :: Python :: 3.10
Classifier: Programming Language :: Python :: 3.11
Classifier: Programming Language :: Python :: 3.12
Classifier: Topic :: Software Development :: Libraries :: Python Modules
Classifier: Topic :: Internet :: WWW/HTTP
Classifier: Topic :: Office/Business :: Financial
Requires-Dist: httpx>=0.24.0
Requires-Dist: typing-extensions>=4.0.0
Requires-Dist: pydantic>=2.11.7
Requires-Python: >=3.9
Project-URL: Bug Tracker, https://github.com/payOSHQ/payos-lib-python/issues
Project-URL: Documentation, https://payos.vn/docs
Project-URL: Homepage, https://payos.vn
Project-URL: Repository, https://github.com/payOSHQ/payos-lib-python
